defi_yields_mcp/__init__.py
defi_yields_mcp/cli.py
defi_yields_mcp-0.1.0.dist-info/METADATA
defi_yields_mcp-0.1.0.dist-info/WHEEL
defi_yields_mcp-0.1.0.dist-info/entry_points.txt
defi_yields_mcp-0.1.0.dist-info/licenses/LICENSE
defi_yields_mcp-0.1.0.dist-info/RECORD
