Metadata-Version: 2.4
Name: defi-yields-mcp
Version: 0.1.0
Summary: Add your description here
License-File: LICENSE
Requires-Python: >=3.10
Requires-Dist: mcp[cli]>=1.6.0
